[
    {
        "positive": 198,
        "negative": 220,
        "fear": 104,
        "anger": 139,
        "anticipation": 106,
        "trust": 121,
        "surprise": 59,
        "sadness": 112,
        "disgust": 138,
        "joy": 119
    },
    {
        "positive": 0.5063938618925832,
        "negative": 0.5626598465473146,
        "fear": 0.2659846547314578,
        "anger": 0.3554987212276215,
        "anticipation": 0.2710997442455243,
        "trust": 0.309462915601023,
        "surprise": 0.15089514066496162,
        "sadness": 0.2864450127877238,
        "disgust": 0.35294117647058826,
        "joy": 0.30434782608695654
    },
    390
]